sphinx_each_pdf/__init__.py
sphinx_each_pdf/convert.py
sphinx_each_pdf/sphinx_each_pdf.py
sphinx_each_pdf-1.0.1.dist-info/METADATA
sphinx_each_pdf-1.0.1.dist-info/WHEEL
sphinx_each_pdf-1.0.1.dist-info/top_level.txt
sphinx_each_pdf-1.0.1.dist-info/RECORD
