Metadata-Version: 2.1
Name: sphinx-each-pdf
Version: 1.0.1
Summary: Tool for converting HTML files to PDFs using Sphinx and Playwright.
Home-page: https://github.com/NeleGALL/each-pdf
Author: NeleGALL
Author-email: ru@burubu.ru
Classifier: Programming Language :: Python :: 3
Classifier: License :: OSI Approved :: MIT License
Classifier: Operating System :: OS Independent
Requires-Python: >=3.8
Requires-Dist: playwright>=1.0.1
